LICENSE
MANIFEST.in
NEWS
README.rst
setup.py
django_international.egg-info/PKG-INFO
django_international.egg-info/SOURCES.txt
django_international.egg-info/dependency_links.txt
django_international.egg-info/top_level.txt
international/__init__.py
international/forms.py
international/models.py
international/settings.py
international/fixtures/countries_fixture.json
tests/__init__.py
tests/models.py
tests/tests.py