Metadata-Version: 1.1
Name: django-international
Version: 0.0.5
Summary: Country and currency data for Django projects
Home-page: https://bitbucket.org/monwara/django-international
Author: Monwara LLC
Author-email: branko@monwara.com
License: BSD
Download-URL: https://bitbucket.org/monwara/django-international/downloads
Platform: UNKNOWN
Classifier: Development Status :: 2 - Pre-Alpha
Classifier: Framework :: Django
Classifier: Environment :: Web Environment
Classifier: Intended Audience :: Developers
Classifier: License :: OSI Approved :: BSD License
